phoopy/__init__.py
phoopy/yaml/__init__.py
phoopy/yaml/yaml_parser.py
phoopy_yaml-1.1.3.dist-info/LICENSE.md
phoopy_yaml-1.1.3.dist-info/METADATA
phoopy_yaml-1.1.3.dist-info/WHEEL
phoopy_yaml-1.1.3.dist-info/top_level.txt
phoopy_yaml-1.1.3.dist-info/RECORD
